{
  "type": "object",
  "title": "Organization",
  "properties": {
    "type": { "type": "string", "default": "Organization", "options": {"hidden": true}},
    "name": { "type": "string" , "title": "Name"},
    "description": { "type": "string", "title": "About the organization"},
    "telephone": { "type" : "string" , "title": "Phone number"},
    "website":  { "type" : "string", "title": "Homepage"},
    "logo": { "type": "string" , "title": "Logo URL"},
    "address": {
      "$ref": "plp-prototypes/basic_postaladdress.json"
    },
    "member": {
      "type": "array",
      "uniqueItems": true,
      "title": "Members of the organization",
      "items": {
        "$ref": "plp-prototypes/_basic_person.json"
      }
    },
    "sameAs": {
      "type": "array",
      "uniqueItems": true,
      "title": "Contact",
      "items":  {
        "$ref": "plp-prototypes/basic_sameas.json"
      }
    },
    "interest": {
      "type": "array",
      "uniqueItems": true,
      "title": "Areas of interest",
      "items":  {
        "$ref": "plp-prototypes/basic_interest.json"
      }
    }
  }
}
